migenpro/__init__.py
migenpro/logger_utils.py
migenpro/main.py
migenpro/ml/__init__.py
migenpro/ml/machine_learning_main.py
migenpro/ml/ml_functions.py
migenpro/ml/parameter_optimisation.py
migenpro/post_analysis/__init__.py
migenpro/post_analysis/ml_model_analysis.py
migenpro/post_analysis/ml_summarise.py
migenpro/post_analysis/uniprot_api_access.py
migenpro/querying/__init__.py
migenpro/querying/genome_annotation.py
migenpro/querying/query_executor.py
migenpro/querying/query_parser.py
migenpro/resources/__init__.py
migenpro/resources/sparql_genome/DomainCopyNumber.sparql
migenpro/resources/sparql_genome/DomainCopyNumber_deprecated.sparql
migenpro/resources/sparql_genome/DomainEvalue.sparql
migenpro/resources/sparql_genome/GenesAroundDomain.sparql
migenpro/resources/sparql_genome/GetGenes.sparql
migenpro/resources/sparql_genome/ProteinDomainsInGene.sparql
migenpro/resources/sparql_genome/__init__.py
migenpro/resources/sparql_genome/featuresInGenomePerGene.sparql
migenpro/resources/sparql_phenotype/__init__.py
migenpro/resources/sparql_phenotype/demo_gram.sparql
migenpro/resources/sparql_phenotype/gram.sparql
migenpro/resources/sparql_phenotype/motility.sparql
migenpro/resources/sparql_phenotype/oxygen.sparql
migenpro/resources/sparql_phenotype/ph.sparql
migenpro/resources/sparql_phenotype/spore.sparql
migenpro/resources/sparql_phenotype/temperature.sparql
migenpro-0.1.3.dist-info/METADATA
migenpro-0.1.3.dist-info/WHEEL
migenpro-0.1.3.dist-info/entry_points.txt
migenpro-0.1.3.dist-info/licenses/LICENSE
migenpro-0.1.3.dist-info/RECORD
