Metadata-Version: 2.4
Name: MiGenPro
Version: 0.1.3
Summary: Microbial Genome Prospecting (MiGenPro) combines phenotype and genomic linked data. Migenpro serves as a framework for the generation of machine learning models that predict microbial traits from genome sequences. 
License: MIT  license
License-File: LICENSE
Author: Mike Loomans
Author-email: mike.loomans@wur.nl
Requires-Python: >=3.11.4,<3.16
Classifier: License :: Other/Proprietary License
Classifier: Programming Language :: Python :: 3
Classifier: Programming Language :: Python :: 3.12
Classifier: Programming Language :: Python :: 3.13
Classifier: Programming Language :: Python :: 3.14
Requires-Dist: PyQt5
Requires-Dist: bio (==1.7.1)
Requires-Dist: cwltool (>=3.1.2)
Requires-Dist: dask
Requires-Dist: docker
Requires-Dist: ete4 (==4.3.0)
Requires-Dist: imbalanced-learn (>=0.13.0)
Requires-Dist: importlib_resources
Requires-Dist: ipython
Requires-Dist: jinja2
Requires-Dist: matplotlib
Requires-Dist: notebook (>=7.4.4,<8.0.0)
Requires-Dist: numpy (>=2.1.3)
Requires-Dist: pandas (>=2.2.3)
Requires-Dist: pyarrow (>=21.0.0)
Requires-Dist: pygenprop
Requires-Dist: pytest (>=8.4.1,<9.0.0)
Requires-Dist: requests
Requires-Dist: scikit-learn (>=1.5.2,<1.6)
Requires-Dist: seaborn (==0.13.2)
Requires-Dist: shap (>=0.48.0)
Project-URL: Homepage, https://gitlab.com/wurssb/migenpro
